{"Visual Studio Code": {"cur_time": 1726821495, "elapsed": 11874}, "Microsoft Text Input Application": {"cur_time": 1726821495, "elapsed": 11874}, "Program Manager": {"cur_time": 1726821495, "elapsed": 11874}, "Microsoft\u200b Edge": {"cur_time": 1726821495, "elapsed": 11383}, "Calculator": {"cur_time": 1726821495, "elapsed": 11192}, "Settings": {"cur_time": 1726821495, "elapsed": 11115}, "GitHub Desktop": {"cur_time": 1726821495, "elapsed": 9811}, "Vivaldi": {"cur_time": 1726821495, "elapsed": 9634}, "Media Player": {"cur_time": 1726821495, "elapsed": 9404}, "NVIDIA GeForce Overlay": {"cur_time": 1726821495, "elapsed": 9404}, "Player.ini": {"cur_time": 1726821495, "elapsed": 9404}, "Clock.ini": {"cur_time": 1726821495, "elapsed": 9404}, "Personal": {"cur_time": 1726821466, "elapsed": 9311}, "Steam": {"cur_time": 1726821344, "elapsed": 9224}, "Discord": {"cur_time": 1726821344, "elapsed": 9213}, "Reddit": {"cur_time": 1726821344, "elapsed": 7664}, "Task Switching": {"cur_time": 1726821484, "elapsed": 7085}, "PowerToys Find My Mouse": {"cur_time": 1726821344, "elapsed": 4162}, "24 h Clock.ini": {"cur_time": 1726821344, "elapsed": 2470}, "templates": {"cur_time": 1726821344, "elapsed": 1888}, "Satisfactory  ": {"cur_time": 1726821344, "elapsed": 1253}, "Setup": {"cur_time": 1726821344, "elapsed": 961}, "Drag": {"cur_time": 1726821344, "elapsed": 496}, "Time-Management-Program": {"cur_time": 1726821344, "elapsed": 120}, "Brave": {"cur_time": 1726821344, "elapsed": 100}, "GitHub": {"cur_time": 1726821344, "elapsed": 87}, "Documents": {"cur_time": 1726821344, "elapsed": 85}, "File Explorer": {"cur_time": 1726821344, "elapsed": 76}, "static": {"cur_time": 1726821344, "elapsed": 65}, "Windows Shell Experience Host": {"cur_time": 1726821344, "elapsed": 58}, "Coding Assignment t1": {"cur_time": 1726821344, "elapsed": 14}, "notificationtoasts_4_desktop": {"cur_time": 1726821344, "elapsed": 6}, "notificationtoasts_5_desktop": {"cur_time": 1726821344, "elapsed": 6}, "Windows-SSD (C:)": {"cur_time": 1726821344, "elapsed": 4}, "Time-Management-Program-Retry": {"cur_time": 1726821344, "elapsed": 1}, "Save As": {"cur_time": 1726821344, "elapsed": 1}, "Desktop": {"cur_time": 1726821344, "elapsed": 0}, "PowerToys.PowerLauncher": {"cur_time": 1726821344, "elapsed": 0}, "Pictures": {"cur_time": 1726821344, "elapsed": 0}}